Workbook

Sheet Калькулятор
B1: Адрес имущества: | C1: г Москва, Волоколамское шоссе, д 71 к 4, кв 12
B3: Калькулятор для страхования физического лица
B5: Выберите условия расчета
B6: Дата рождения | C6: 25003 | D6: =IF(ORG.OPENOFFICE.YEARS(C6,TODAY(),0)>60,"СОГЛАСОВАНИЕ РГ","") | E6: <= | F6: Выбор возраста
B7: Возраст | C7: =ORG.OPENOFFICE.YEARS(C6,TODAY(),0) -> 58
B8: Возраст | C8: =VLOOKUP(ORG.OPENOFFICE.YEARS(C6,TODAY(),0),КИС!B17:E34,3,1) -> 56-58
B9: Выберите пол | C9: Женщина | E9: <= | F9: Выбор пола
B10: Занимается ли застрахованный спортом? | C10: Нет | E10: <=
B11: Род деятельности | C11: Нерисковая | E11: <=
B12: Конструктив покрыт? | C12: =VLOOKUP(C18,Справочно!$L$2:$N$15,3,0) -> Да
B13: Тип перекрытий | C13: Каменный | E13: <= | F13: Без данных указывается «каменный»
B14: Тип помещения | C14: Квартира | D14: =IF(AND(C14="дом",C13="деревянный"),"СОГЛАСОВАНИЕ РГ","") | E14: <=
B15: Год объекта | C15: 2025 | E15: <= | F15: Год примерный нужно хотя бы
B16: Возраст объекта | C16: =VLOOKUP(YEAR(TODAY())-C15,КИС!A60:B64,2,1) -> 0-20
B17: Терроризм (имущество) | C17: Нет
B18: Банк | C18: Сбербанк | E18: <= | F18: Считаем Сбер, Тбанк, Юникредит, Райф — остальное не страхуем.
B19: РВД | C19: 5
B20: Прибыль и прочее | C20: =IF(C18=Справочно!L12,IF(ORG.OPENOFFICE.YEARS(C6,TODAY(),0)>40,Справочно!O12,Справочно!P12), VLOOKUP(C18,Справочно!L2:M16,2,0))-C23 -> 5
B21: Банк КВ | C21: 0
B22: Партнер | C22: АСТ
B23: Партнерское КВ | C23: 50
B24: Партнерское КВ АСТ | C24: 0
B25: Общая нагрузка | C25: =IF(C22="иной",SUM(C23,C21,C20,C19),SUM(C19:C24)) -> 60
B27: НС| Поправка | C27: 0 | D27: =C27*IF(D37="нет","n/a",VLOOKUP(C8,КИС!$A$15:$L$34,IF(C9="Мужчина",11,12),0)*VLOOKUP(C11,КИС!B8:C9,2,0)*VLOOKUP(C10,КИС!B11:C12,2,0)*C36) -> 0
B28: Имущество |Поправка | C28: 0 | D28: =IFERROR(C28*C36*IF(D39="Нет","n/a",IF(C12="Нет",КИС!K48,КИС!K47)*VLOOKUP(C13,КИС!B51:C53,2,0)*VLOOKUP(C14,КИС!B55:C58,2,0)*VLOOKUP(C16,КИС!B60:C64,2,0)*IF(C17="Нет",1,КИС!C50)),0) -> 0
B29: Титул |Поправка | C29: 0
B31: Смотрим цену РНПК (НС)? | C31: Да | E31: <=
B33: Результат | D33: Покрытие: | G33: Тариф | H33: Тариф нетто | I33: РНПК | J33: РНПК+РВД | K33: Дельта | L33: Абсолют дельта | M33: Цена РНПК | N33: Цена РНПК + КВ | O33: Тариф РНПК брутто
B34: Остаток кредита | C34: 1990000 | E34: <= | F34: в этом блоке требуется ввести страховую сумму, в соответствии с которой, рассчитается страховой взнос.
B35: Ставка банка (к ОСЗ прибавка) | C35: =VLOOKUP(C18,Справочно!L2:Q16,6,0)% -> 0
B36: Страховая сумма | C36: =C34*(1+C35) -> 1990000
B37: НС |Итоговый тариф, % от страховой суммы | C37: =IF(D37="нет","n/a",IF(C31="да",MAX(G37,O37),G37)) -> 0.006104 | D37: Да | G37: =ROUND(VLOOKUP(C8,КИС!$A$15:$L$34,IF(C9="Мужчина",11,12),0)*VLOOKUP(C11,КИС!B8:C9,2,0)*VLOOKUP(C10,КИС!B11:C12,2,0)*(1+C27),7) -> 0.00495 | H37: =G37*(1-C43) -> 0.002475 | I37: =ROUND(VLOOKUP(ORG.OPENOFFICE.YEARS(C6,TODAY(),0),РНПК!A1:C49,IF(C9="женщина",3,2),0)/100,6) -> 0.003052 | J37: =I37*1.05 -> 0.0032046 | K37: =IFERROR(H37-J37,"") -> -0.0007296 | L37: =$C$36*K37 -> -1451.904 | M37: =I37*$C$36 -> 6073.48 | N37: =M37/(1-C43) -> 12146.96 | O37: =ROUND(N37/C36,7) -> 0.006104
B38: Страховой взнос | C38: =IF(D37="Нет","n/a",C37*C36) -> 12146.96 | W38: =IF(D37="ДА",1,0) -> 1
B39: Имущество |Итоговый тариф, % от страховой суммы | C39: =IF(D39="нет","n/a",MAX(G39,O39)) -> 0.0005 | D39: Да | G39: =IF(D39="Нет","n/a",ROUND(IF(C12="Нет",КИС!K48,КИС!K47)*VLOOKUP(C13,КИС!B51:C53,2,0)*VLOOKUP(C14,КИС!B55:C58,2,0)*VLOOKUP(C16,КИС!B60:C64,2,0)*IF(C17="Нет",1,КИС!C50)*(1+C28),7)) -> 0.000476 | H39: =G39*(1-C43) -> 0.000238 | I39: =IF(C14="квартира",Справочно!G4,VLOOKUP(C13,Справочно!F5:G7,2,0)) -> 0,025% | J39: =I39*1.05 -> 0.0002625 | K39: =IFERROR(H39-J39,"") -> -2.45e-05 | L39: =$C$36*K39 -> -48.755 | M39: =I39*$C$36 -> 497.5 | N39: =M39/(1-C43) -> 995 | O39: =ROUND(N39/C36,7) -> 0.0005
B40: Страховой взнос | C40: =IF(D39="Нет","n/a",C39*C36) -> 995 | W40: =IF(D39="ДА",1,0) -> 1
B41: Титул |Итоговый тариф, % от страховой суммы | C41: =IF(D41="нет","n/a",MAX(G41,O41)) -> n/a | D41: Нет | G41: =ROUND(КИС!K73*(1+C29),7) -> 0.00165 | H41: =G41*(1-C43) -> 0.000825 | I41: 0.0008 | J41: =I41*1.05 -> 0.00084 | K41: =IFERROR(H41-J41,"") -> -1.5e-05 | L41: =$C$36*K41 -> -29.85 | M41: =I41*$C$36 -> 1592 | N41: =M41/(1-C43) -> 3184 | O41: =ROUND(N41/C36,7) -> 0.0016
B42: Страховой взнос | C42: =IF(D41="Нет","n/a",C41*C36) -> n/a | G42: =G39+G41 -> 0.002126 | H42: =H39+H41 -> 0.001063 | I42: 0.001 | J42: =I42*1.05 -> 0.00105 | K42: =IFERROR(H42-J42,"") -> 1.3e-05 | L42: =$C$36*K42 -> 25.87 | M42: =I42*$C$36 -> 1990 | N42: =M42/(1-C43) -> 3980 | O42: =ROUND(N42/C36,7) -> 0.002 | W42: =IF(D41="ДА",1,0) -> 0
B43: Партнерское КВ | C43: =C23/100 -> 0.5
B44: Всего | Страховой взнос по договору | C44: =SUMIFS(C37:C44,W37:W44,1) -> 13141.96 | L44: =SUM(L37,IF(D41="нет",L39,L42)) -> -1500.659
B48: Результат
B49: Остаток кредита | C49: =C34 -> 1990000
B50: Ставка банка (к ОСЗ прибавка) | C50: =C35 -> 0
B51: Страховая сумма | C51: =C49*(1+C50) -> 1990000
B52: =B19 -> РВД | C52: =C19 -> 5
B53: =B20 -> Прибыль и прочее | C53: =C20 -> 5
B54: Партнерское КВ | C54: =SUM(C23:C24) -> 50
B55: Общая нагрузка | C55: =C25 -> 60
B56: НС| Поправка | C56: =C27 -> 0
B57: Имущество |Поправка | C57: =C28 -> 0
B58: Титул |Поправка | C58: =C29 -> 0
C59: НС | D59: Имущество | E59: Титул | F59: Имущество + титул
B60: Покрытие: | C60: =D37 -> Да | D60: =D39 -> Да | E60: =D41 -> Нет | F60: =IF(AND(D60="Да",E60="Да")=1,"Да","Нет") -> Нет
B61: Тариф брутто | C61: =IF(C60="нет","n/a",ROUND(VLOOKUP(C8,КИС!$A$15:$L$34,IF(C9="мужчина",11,12),0)*VLOOKUP(C11,КИС!B8:C9,2,0)*VLOOKUP(C10,КИС!B11:C12,2,0)*(1+C27),7)) -> 0.00495 | D61: =IF(D39="Нет","n/a",ROUND(IF(C12="Нет",КИС!K48,КИС!K47)*VLOOKUP(C13,КИС!B51:C53,2,0)*VLOOKUP(C14,КИС!B55:C58,2,0)*VLOOKUP(C16,КИС!B60:C64,2,0)*IF(C17="Нет",1,КИС!C50)*(1+C28),7)) -> 0.000476 | E61: =IF(D41="нет","n/a",КИС!K73*(1+C29)) -> n/a | F61: =IF(F60="нет","n/a",D61+E61) -> n/a
B62: Тариф брутто РНПК | C62: =IF(C60="нет","n/a",C64/(1-$C$43)) -> 0.006104 | D62: =O39 -> 0.0005 | E62: =IF(D41="нет","n/a",E64/(1-$C$43)) -> n/a | F62: =IF(F60="нет","n/a",F64/(1-$C$43)) -> n/a
B63: Тариф нетто | C63: =IF(C60="нет","n/a",G37*(1-C43)) -> 0.002475 | D63: =IF(D60="нет","n/a",G39*(1-C43)) -> 0.000238 | E63: =IF(D41="нет","n/a",G41*(1-C43)) -> n/a | F63: =IF(F60="нет","n/a",D63+E63) -> n/a
B64: Тариф нетто РНПК | C64: =IF(C60="нет","n/a",VLOOKUP(ORG.OPENOFFICE.YEARS(C6,TODAY(),0),РНПК!A1:C49,IF(C9="женщина",3,2),0)/100) -> 0.003052 | D64: =IF(D60="нет","n/a",IF(C14="квартира",Справочно!G4,VLOOKUP(C13,Справочно!F5:G7,2,0))) -> 0,025% | E64: =IF(D41="нет","n/a",0.08%) -> n/a | F64: =IF(F60="нет","n/a",0.1%) -> n/a
B65: Тариф РНПК + РВД 5% | C65: =IF(C60="нет","n/a",C64*1.05) -> 0.0032046 | D65: =IF(D60="нет","n/a",D64*1.05) -> 0.0002625 | E65: =IF(E60="нет","n/a",E64*1.05) -> n/a | F65: =IF(F60="нет","n/a",F64*1.05) -> n/a
B66: Дельта абсолют | C66: =IF(C60="нет","n/a",(C63-C65)*$C$51) -> -1451.904 | D66: =IF(D60="нет","n/a",(D63-D64)*$C$51) -> -23.88 | E66: =IF(E60="нет","n/a",(E63-E65)*$C$51) -> n/a | F66: =IF(F60="нет","n/a",(F63-F65)*$C$51) -> n/a
B67: Тариф брутто | C67: =IF(C60="нет","n/a",MAX(C61,C62)) -> 0.006104 | D67: =IF(D60="нет","n/a",IF(D60="нет","n/a",MAX(D61,D62))) -> 0.0005 | E67: =IF(E60="нет","n/a",IF(E60="нет","n/a",MAX(E61,E62))) -> n/a | F67: =IF(F60="нет","n/a",IF(F60="нет","n/a",MAX(F61,F62))) -> n/a
B68: Премия брутто | C68: =IFERROR($C$51*C67,"n/a") -> 12146.96 | D68: =IF(D60="нет","n/a",IFERROR($C$51*D67,"n/a")) -> 995 | E68: =IFERROR($C$51*E67,"n/a") -> n/a | F68: =IFERROR($C$51*F67,"n/a") -> n/a
B69: ="КВ посредника "&(C43*100)&"%" -> КВ посредника 50% | C69: =IFERROR(C68*$C$43,"n/a") -> 6073.48 | D69: =IFERROR(D68*$C$43,"n/a") -> 497.5 | E69: =IFERROR(E68*$C$43,"n/a") -> n/a | F69: =IFERROR(F68*$C$43,"n/a") -> n/a
B70: Нетто-тариф | C70: =C63 -> 0.002475 | D70: =D63 -> 0.000238 | E70: =E63 -> n/a | F70: =F63 -> n/a
B71: Нетто-премия | C71: =IFERROR(C68-C69,"n/a") -> 6073.48 | D71: =IFERROR(D68-D69,"n/a") -> 497.5 | E71: =IFERROR(E68-E69,"n/a") -> n/a | F71: =IFERROR(F68-F69,"n/a") -> n/a
B72: Нетто-премия по доле Перестрахователя | C72: =IFERROR(C71*10%,"n/a") -> 607.348 | D72: =IFERROR(D71*10%,"n/a") -> 49.75 | E72: =IFERROR(E71*10%,"n/a") -> n/a | F72: =IFERROR(F71*10%,"n/a") -> n/a
B73: Нетто-премия по доле Перестраховщика | C73: =IFERROR(C71*90%,"n/a") -> 5466.132 | D73: =IFERROR(D71*90%,"n/a") -> 447.75 | E73: =IFERROR(E71*90%,"n/a") -> n/a | F73: =IFERROR(F71*90%,"n/a") -> n/a
B74: Тариф нетто РНПК | C74: =C64 -> 0.003052 | D74: =D64 -> 0,025% | E74: =E64 -> n/a | F74: =F64 -> n/a
B75: Фин. результат | C75: =IFERROR(C72+$C$51*(C70-C74),"n/a") -> -540.882 | D75: =IFERROR(D72+$C$51*(D70-D74)*90%,"n/a") -> 28.258 | E75: =IFERROR(E72+$C$51*(E70-E74),"n/a") -> n/a | F75: =IFERROR(F72+$C$51*(F70-F74),"n/a") -> n/a
B76: Всего | Страховой взнос по договору | C76: =IF(F60="да",SUMIFS(C68:F68,C60:F60,"да")-SUMIFS(D68:E68,D60:E60,"да"),SUMIFS(C68:F68,C60:F60,"да")) -> 13141.96
B78: Скидка за счет КВ | C78: 0.5
B79: Всего | Страховой взнос по договору | C79: =C76*(1-C43)/(1-C78) -> 13141.96
B82: Результат | D82: Покрытие:
B83: Остаток кредита | C83: =C34 -> 1990000
B84: Ставка банка (к ОСЗ прибавка) | C84: =C35 -> 0
B85: Страховая сумма | C85: =C36 -> 1990000
B86: НС |Итоговый тариф, % от страховой суммы | C86: =C37*(1-C43)/(1-C78) -> 0.006104 | D86: =D37 -> Да
B87: Страховой взнос | C87: =IF(D86="Нет","n/a",C86*C85) -> 12146.96
B88: Имущество |Итоговый тариф, % от страховой суммы | C88: =IFERROR(C39*(1-C43)/(1-C78),"n/a") -> 0.0005 | D88: =D39 -> Да
B89: Страховой взнос | C89: =IF(D88="Нет","n/a",C88*C85) -> 995
B90: Титул |Итоговый тариф, % от страховой суммы | C90: =IF(D90="нет","n/a",MAX(G90,O90)) -> n/a | D90: =D41 -> Нет
B91: Страховой взнос | C91: =IF(D90="Нет","n/a",C90*C85) -> n/a
B92: Партнерское КВ | C92: =C78 -> 0.5
B93: Всего | Страховой взнос по договору | C93: =SUM(C87,C89,C91) -> 13141.96
B95: Адрес имущества: | C95: =C1 -> г Москва, Волоколамское шоссе, д 71 к 4, кв 12
B97: СОЗАЕМЩИК
B98: Есть? | C98: Да
B99: Калькулятор для страхования физического лица
B101: Выберите условия расчета
B102: Дата рождения | C102: 29395
B103: Возраст | C103: =VLOOKUP(ORG.OPENOFFICE.YEARS(C102,TODAY(),0),КИС!B17:E34,3,1) -> 44-46
B104: Выберите пол | C104: Женщина
B105: Занимается ли застрахованный спортом? | C105: Нет
B106: Род деятельности | C106: Нерисковая
F107: Тариф | G107: Тариф нетто | H107: РНПК | J107: Дельта | L107: Цена РНПК | M107: Цена РНПК + КВ | N107: Тариф РНПК брутто
B108: НС| Поправка | C108: -0.1
B110: Результат
B111: НС |Итоговый тариф, % от страховой суммы | C111: =VLOOKUP(C103,КИС!$A$15:$L$34,IF(C104="Мужчина",11,12),0)*VLOOKUP(C106,КИС!B8:C9,2,0)*VLOOKUP(C105,КИС!B11:C12,2,0)*(1+C108) -> 0.00224775 | F111: =VLOOKUP(C103,КИС!$A$15:$L$34,IF(C104="Мужчина",11,12),0)*VLOOKUP(C106,КИС!B8:C9,2,0)*VLOOKUP(C105,КИС!B11:C12,2,0)*(1+C27) -> 0.0024975 | G111: =F111*(1-C43) -> 0.00124875 | H111: =VLOOKUP(ORG.OPENOFFICE.YEARS(C102,TODAY(),0),РНПК!A1:C49,IF(C104="женщина",3,2),0)/100 -> 0.00119 | J111: =IFERROR(G111-H111,"") -> 5.875e-05 | L111: =H111*$C$36 -> 2368.1 | M111: =L111/(1-C43) -> 4736.2 | N111: =M111/C36 -> 0.00238
B112: Страховой взнос | C112: =C36*C111 -> 4473.0225
B113: Всего | Страховой взнос по договору | C113: =SUMIFS(C111:C113,L111:L113,1) -> 0
B116: Доля заемщика
B117: 0.8 | C117: =C38*B117 -> 9717.568
...

Sheet КИС
B1: Пакет рисков базовый | T1: Нагрузка | U1: Брутто-ставка (страховой тариф) | V1: Поправочный коэффициент | X1: К7 - Коэффициент риска, зависящий от включения в страховое покрытие возмещение вреда отделке и инженерному оборудованию (сетям): 1,15.
B2: СТС | C2: 0.75 | E2: КВ | T2: 1 | U2: 0.0343 | V2: 0.202 | X2: К8 - Коэффициент риска, учитывающий страхование с неагрегатной страховой суммой: 1,00.
C3: 0.05 | E3: РВД | T3: 2 | U3: 0.0347 | V3: 0.204 | X3: К9 – Коэффициент, учитывающий особенности территории страхования: 0,7-2,5.
T4: 3 | U4: 0.0351 | V4: 0.206 | X4: К10 - Коэффициент, применяемый при наличии важных факторов, влияющих на наступление страхового события: 0,3-4,0.
C5: НС | T5: 4 | U5: 0.0354 | V5: 0.208 | X5: К11 - Коэффициент риска, применяемый при ограничении числа внешних факторов, влияющих на наступление страхового события (при сужении страхового покрытия): 0,05-0,99.
B6: Тариф | C6: 0.009 | T6: 5 | U6: 0.0358 | V6: 0.211 | X6: К12 - Коэффициент, учитывающий величину страховой суммы: 0,5-3,0.
B7: Деятельность | G7: РВД | H7: 5 | I7: РВД | J7: 5 | K7: РВД | L7: =Калькулятор!C19+Калькулятор!C20 -> 10 | M7: РВД | N7: 5 | T7: 6 | U7: 0.0362 | V7: 0.213 | X7: К13 - Коэффициент риска, зависящий от предшествующей страховой истории: 0,7-5,0.
B8: Нерисковая | C8: 1 | G8: Банк % | H8: 50 | I8: Банк КВ | J8: 0 | K8: Банк КВ | L8: =Калькулятор!C21 -> 0 | M8: Банк КВ | N8: 40 | T8: 7 | U8: 0.0366 | V8: 0.215 | X8: К14 - Коэффициент, применяемый в случае снижения комиссионного вознаграждения или изменения структуры тарифа в части снижения доли нагрузки: 0,2-1,0.
B9: Опасная | C9: 1.5
B10: Спорт | G10: Партнерское КВ | H10: 25 | I10: Партнерское КВ | J10: 30 | K10: Партнерское КВ | L10: =Калькулятор!C23+Калькулятор!C24 -> 50 | M10: Партнерское КВ | N10: 20 | T10: 8 | U10: 0.037 | V10: 0.217 | X10: К15 - Коэффициент, учитывающий наличие в застрахованном помещении/строении средств пожаротушения: 0,70-1,00.
B11: Нет | C11: 1 | H11: =SUM(H7:H10) -> 80 | J11: =SUM(J7:J10) -> 35 | L11: =SUM(L7:L10) -> 60 | N11: =SUM(N7:N10) -> 65 | T11: 9 | U11: 0.0374 | V11: 0.22 | X11: К16 - Коэффициент риска, зависящий от наличия источников открытого огня и газопровода: 1-10.
B12: Да | C12: 1.5
T14: 10 | U14: 0.0378 | V14: 0.222 | X14: К17 - Коэффициент риска, зависящий от наличия средств охраны на объекте: 0,8-1,2.
B15: Возраст | E15: Коэффициент | G15: Тариф | K15: ="Партнерский Тариф с РВД " &L11 &"%" -> Партнерский Тариф с РВД 60% | S15: Тариф в пере с учетом нашего КВ | T15: 11 | U15: 0.0382 | V15: 0.225 | X15: К18 - Коэффициент риска, зависящий от характера местонахождения земельного участка: 0,3-4,0.
E16: Мужчина | F16: Женщина | G16: Мужчина | H16: Женщина | K16: Мужчина | L16: Женщина | T16: 12 | U16: 0.0386 | V16: 0.227 | X16: К19 - Коэффициент риска, зависящий от вида разрешенного использования земельного участка: 1-4.
A17: =B17&"-"&C17 -> 18-20 | B17: 18 | C17: 20 | D17: 18-20 | E17: 0.2 | F17: 0.2 | G17: =E17*$C$6 -> 0.0018 | H17: =F17*$C$6 -> 0.0018 | K17: =G17*VLOOKUP($L$11,T:V,3,0) -> 0.0009 | L17: =H17*VLOOKUP($L$11,T:V,3,0) -> 0.0009 | M17: =K17*$L$10% -> 0.00045 | N17: =L17*$L$10% -> 0.00045 | S17: 0.04 | T17: 13 | U17: 0.0391 | V17: 0.23 | X17: К20 - Коэффициент, учитывающий проведение ремонтных, отделочных или строительных работ: 1,2.
A18: =B18&"-"&C18 -> 21-25 | B18: 21 | C18: 25 | D18: 21-25 | E18: 0.23 | F18: 0.215 | G18: =E18*$C$6 -> 0.00207 | H18: =F18*$C$6 -> 0.001935 | K18: =G18*VLOOKUP($L$11,T:V,3,0) -> 0.001035 | L18: =H18*VLOOKUP($L$11,T:V,3,0) -> 0.0009675 | M18: =K18*$L$10% -> 0.0005175 | N18: =L18*$L$10% -> 0.00048375 | S18: 0.025 | T18: 14 | U18: 0.0395 | V18: 0.233 | X18: К21 - Коэффициент, применяемый для установления маркетинговой цены страхового продукта: 0,7-3,0.
A19: =B19&"-"&C19 -> 26-27 | B19: =C18+1 -> 26 | C19: 27 | D19: 26-27 | E19: 0.26 | F19: 0.23 | G19: =E19*$C$6 -> 0.00234 | H19: =F19*$C$6 -> 0.00207 | K19: =G19*VLOOKUP($L$11,T:V,3,0) -> 0.00117 | L19: =H19*VLOOKUP($L$11,T:V,3,0) -> 0.001035 | M19: =K19*$L$10% -> 0.000585 | N19: =L19*$L$10% -> 0.0005175 | T19: 15 | U19: 0.04 | V19: 0.235
A20: =B20&"-"&C20 -> 28-29 | B20: =C19+1 -> 28 | C20: 29 | D20: 28-29 | E20: 0.27 | F20: 0.24 | G20: =E20*$C$6 -> 0.00243 | H20: =F20*$C$6 -> 0.00216 | K20: =G20*VLOOKUP($L$11,T:V,3,0) -> 0.001215 | L20: =H20*VLOOKUP($L$11,T:V,3,0) -> 0.00108 | M20: =K20*$L$10% -> 0.0006075 | N20: =L20*$L$10% -> 0.00054 | T20: 16 | U20: 0.0405 | V20: 0.238 | X20: НС
A21: =B21&"-"&C21 -> 30-31 | B21: =C20+1 -> 30 | C21: 31 | D21: 30-31 | E21: 0.295 | F21: 0.25 | G21: =E21*$C$6 -> 0.002655 | H21: =F21*$C$6 -> 0.00225 | K21: =G21*VLOOKUP($L$11,T:V,3,0) -> 0.0013275 | L21: =H21*VLOOKUP($L$11,T:V,3,0) -> 0.001125 | M21: =K21*$L$10% -> 0.00066375 | N21: =L21*$L$10% -> 0.0005625 | T21: 17 | U21: 0.041 | V21: 0.241 | X21: К4 - Коэффициент риска, учитывающий страхование с неагрегатной страховой суммой: 1,00.
A22: =B22&"-"&C22 -> 32-33 | B22: =C21+1 -> 32 | C22: 33 | D22: 32-33 | E22: 0.305 | F22: 0.265 | G22: =E22*$C$6 -> 0.002745 | H22: =F22*$C$6 -> 0.002385 | K22: =G22*VLOOKUP($L$11,T:V,3,0) -> 0.0013725 | L22: =H22*VLOOKUP($L$11,T:V,3,0) -> 0.0011925 | M22: =K22*$L$10% -> 0.00068625 | N22: =L22*$L$10% -> 0.00059625 | T22: 18 | U22: 0.0415 | V22: 0.244 | X22: К5 - Коэффициент, применяемый для установления маркетинговой цены страхового продукта:0,70-3,0.
A23: =B23&"-"&C23 -> 34-35 | B23: =C22+1 -> 34 | C23: 35 | D23: 34-35 | E23: 0.32 | F23: 0.28 | G23: =E23*$C$6 -> 0.00288 | H23: =F23*$C$6 -> 0.00252 | K23: =G23*VLOOKUP($L$11,T:V,3,0) -> 0.00144 | L23: =H23*VLOOKUP($L$11,T:V,3,0) -> 0.00126 | M23: =K23*$L$10% -> 0.00072 | N23: =L23*$L$10% -> 0.00063 | T23: 19 | U23: 0.042 | V23: 0.247 | X23: К6 - Коэффициент, применяемый при наличии важных факторов, влияющих на наступление страхового события: 0,3-4,0.
A24: =B24&"-"&C24 -> 36-37 | B24: =C23+1 -> 36 | C24: 37 | D24: 36-37 | E24: 0.34 | F24: 0.3 | G24: =E24*$C$6 -> 0.00306 | H24: =F24*$C$6 -> 0.0027 | K24: =G24*VLOOKUP($L$11,T:V,3,0) -> 0.00153 | L24: =H24*VLOOKUP($L$11,T:V,3,0) -> 0.00135 | M24: =K24*$L$10% -> 0.000765 | N24: =L24*$L$10% -> 0.000675 | T24: 20 | U24: 0.0425 | V24: 0.25 | X24: К7 - Коэффициент риска, применяемый при ограничении числа внешних факторов, влияющих на наступление страхового события (при сужении страхового покрытия): 0,05-0,99.
A25: =B25&"-"&C25 -> 38-39 | B25: =C24+1 -> 38 | C25: 39 | D25: 38-39 | E25: 0.375 | F25: 0.33 | G25: =E25*$C$6 -> 0.003375 | H25: =F25*$C$6 -> 0.00297 | K25: =G25*VLOOKUP($L$11,T:V,3,0) -> 0.0016875 | L25: =H25*VLOOKUP($L$11,T:V,3,0) -> 0.001485 | M25: =K25*$L$10% -> 0.00084375 | N25: =L25*$L$10% -> 0.0007425 | T25: 21 | U25: 0.043 | V25: 0.253 | X25: К8 - Коэффициент, учитывающий величину страховой суммы: 0,50-3,0.
A26: =B26&"-"&C26 -> 40-41 | B26: =C25+1 -> 40 | C26: 41 | D26: 40-41 | E26: 0.42 | F26: 0.38 | G26: =E26*$C$6 -> 0.00378 | H26: =F26*$C$6 -> 0.00342 | K26: =G26*VLOOKUP($L$11,T:V,3,0) -> 0.00189 | L26: =H26*VLOOKUP($L$11,T:V,3,0) -> 0.00171 | M26: =K26*$L$10% -> 0.000945 | N26: =L26*$L$10% -> 0.000855 | T26: 22 | U26: 0.0436 | V26: 0.256 | X26: К9 - Коэффициент риска, зависящий от предшествующей страховой истории: 0,70-5,0.
A27: =B27&"-"&C27 -> 42-43 | B27: =C26+1 -> 42 | C27: 43 | D27: 42-43 | E27: 0.5 | F27: 0.44 | G27: =E27*$C$6 -> 0.0045 | H27: =F27*$C$6 -> 0.00396 | K27: =G27*VLOOKUP($L$11,T:V,3,0) -> 0.00225 | L27: =H27*VLOOKUP($L$11,T:V,3,0) -> 0.00198 | M27: =K27*$L$10% -> 0.001125 | N27: =L27*$L$10% -> 0.00099 | T27: 23 | U27: 0.0442 | V27: 0.26 | X27: К10 - Коэффициент, применяемый в случае снижения комиссионного вознаграждения или изменения структуры тарифа в части снижения доли нагрузки:0,20-1,00.
A28: =B28&"-"&C28 -> 44-46 | B28: =C27+1 -> 44 | C28: 46 | D28: 44-46 | E28: 0.58 | F28: 0.555 | G28: =E28*$C$6 -> 0.00522 | H28: =F28*$C$6 -> 0.004995 | K28: =G28*VLOOKUP($L$11,T:V,3,0) -> 0.00261 | L28: =H28*VLOOKUP($L$11,T:V,3,0) -> 0.0024975 | M28: =K28*$L$10% -> 0.001305 | N28: =L28*$L$10% -> 0.00124875 | T28: 24 | U28: 0.0447 | V28: 0.263 | X28: К11 - Коэффициент риска, учитывающий наличие заболеваний из перечня социально значимых заболеваний, а также цирроза печени, сердечно-сосудистых заболеваний: 1,00-10,0.
A29: =B29&"-"&C29 -> 47-49 | B29: =C28+1 -> 47 | C29: 49 | D29: 47-49 | E29: 0.67 | F29: 0.655 | G29: =E29*$C$6 -> 0.00603 | H29: =F29*$C$6 -> 0.005895 | K29: =G29*VLOOKUP($L$11,T:V,3,0) -> 0.003015 | L29: =H29*VLOOKUP($L$11,T:V,3,0) -> 0.0029475 | M29: =K29*$L$10% -> 0.0015075 | N29: =L29*$L$10% -> 0.00147375 | T29: 25 | U29: 0.0453 | V29: 0.267 | X29: К12 - Коэффициент риска, зависящий от вида деятельности застрахованных лиц: 0,50-10,0.
A30: =B30&"-"&C30 -> 50-52 | B30: =C29+1 -> 50 | C30: 52 | D30: 50-52 | E30: 0.81 | F30: 0.795 | G30: =E30*$C$6 -> 0.00729 | H30: =F30*$C$6 -> 0.007155 | K30: =G30*VLOOKUP($L$11,T:V,3,0) -> 0.003645 | L30: =H30*VLOOKUP($L$11,T:V,3,0) -> 0.0035775 | M30: =K30*$L$10% -> 0.0018225 | N30: =L30*$L$10% -> 0.00178875 | T30: 26 | U30: 0.0459 | V30: 0.27 | X30: К13 - Коэффициент риска, зависящий от занятий спортом Застрахованным лицом: 1,00-5,00.
A31: =B31&"-"&C31 -> 53-55 | B31: =C30+1 -> 53 | C31: 55 | D31: 53-55 | E31: 0.93 | F31: 0.93 | G31: =E31*$C$6 -> 0.00837 | H31: =F31*$C$6 -> 0.00837 | K31: =G31*VLOOKUP($L$11,T:V,3,0) -> 0.004185 | L31: =H31*VLOOKUP($L$11,T:V,3,0) -> 0.004185 | M31: =K31*$L$10% -> 0.0020925 | N31: =L31*$L$10% -> 0.0020925 | T31: 27 | U31: 0.0466 | V31: 0.274
A32: =B32&"-"&C32 -> 56-58 | B32: 56 | C32: 58 | D32: 56-58 | E32: 1.1 | F32: 1.1 | G32: =E32*$C$6 -> 0.0099 | H32: =F32*$C$6 -> 0.0099 | K32: =G32*VLOOKUP($L$11,T:V,3,0) -> 0.00495 | L32: =H32*VLOOKUP($L$11,T:V,3,0) -> 0.00495 | M32: =K32*$L$10% -> 0.002475 | N32: =L32*$L$10% -> 0.002475 | T32: 28 | U32: 0.0472 | V32: 0.278
A33: =B33&"-"&C33 -> 59-63 | B33: 59 | C33: 63 | D33: 59-63 | E33: 1.2 | F33: 1.2 | G33: =E33*$C$6 -> 0.0108 | H33: =F33*$C$6 -> 0.0108 | K33: =G33*VLOOKUP($L$11,T:V,3,0) -> 0.0054 | L33: =H33*VLOOKUP($L$11,T:V,3,0) -> 0.0054 | M33: =K33*$L$10% -> 0.0027 | N33: =L33*$L$10% -> 0.0027 | T33: 29 | U33: 0.0479 | V33: 0.282
A34: =B34&"-"&C34 -> 64-65 | B34: 64 | C34: 65 | D34: 64-65 | E34: 1.3 | F34: 1.3 | G34: =E34*$C$6 -> 0.0117 | H34: =F34*$C$6 -> 0.0117 | K34: =G34*VLOOKUP($L$11,T:V,3,0) -> 0.00585 | L34: =H34*VLOOKUP($L$11,T:V,3,0) -> 0.00585 | M34: =K34*$L$10% -> 0.002925 | N34: =L34*$L$10% -> 0.002925 | T34: 30 | U34: 0.0486 | V34: 0.286
Q35: 0.1 | R35: 0.05 | T35: 31 | U35: 0.0493 | V35: 0.29
T36: 32 | U36: 0.05 | V36: 0.294
H37: 2627900.3 | I37: =H37*I27 -> 0 | M37: =H37*M27 -> 2956.3879 | T37: 33 | U37: 0.0507 | V37: 0.299
T38: 34 | U38: 0.0515 | V38: 0.303
T39: 35 | U39: 0.0523 | V39: 0.308
T40: 36 | U40: 0.0531 | V40: 0.313
C41: Имво | G41: РВД | H41: 5 | I41: РВД | J41: 5 | K41: РВД | L41: =Калькулятор!C19+Калькулятор!C20 -> 10 | M41: РВД | N41: 5 | T41: 37 | U41: 0.054 | V41: 0.317
G42: Банк % | H42: 50 | I42: Банк КВ | J42: 0 | K42: Банк КВ | L42: =Калькулятор!C21 -> 0 | M42: Банк КВ | N42: 40 | T42: 38 | U42: 0.0548 | V42: 0.323
G43: Партнерское КВ | H43: 25 | I43: Партнерское КВ | J43: 0 | K43: Партнерское КВ | L43: =Калькулятор!C23+Калькулятор!C24 -> 50 | M43: Партнерское КВ | N43: 25 | T43: 39 | U43: 0.0557 | V43: 0.328
H44: =SUM(H41:H43) -> 80 | J44: =SUM(J41:J43) -> 5 | L44: =SUM(L41:L43) -> 60 | N44: =SUM(N41:N43) -> 70 | T44: 40 | U44: 0.0567 | V44: 0.333
T45: 41 | U45: 0.0576 | V45: 0.339
G46: Тариф | I46: ="Тариф с РВД " &J44 &"%" -> Тариф с РВД 5% | K46: ="Партнерский Тариф с РВД " &L43 &"%" -> Партнерский Тариф с РВД 50% | M46: ="Партнерский Тариф с РВД " &N43 &"%" -> Партнерский Тариф с РВД 25% | T46: 42 | U46: 0.0586 | V46: 0.345
B47: Тариф | C47: 0.0017 | G47: =C47 -> 0.0017 | I47: =G47*VLOOKUP($J$44,T:V,3,0) -> 0.0003587 | K47: =G47*VLOOKUP($L$44,T:V,3,0) -> 0.00085 | M47: =G47*VLOOKUP($N$44,T:V,3,0) -> 0.0011339 | T47: 43 | U47: 0.0596 | V47: 0.351
B48: Тариф без констр | C48: 0.0015 | G48: =C48 -> 0.0015 | I48: =G48*VLOOKUP($J$44,T:V,3,0) -> 0.0003165 | K48: =G48*VLOOKUP($L$44,T:V,3,0) -> 0.00075 | M48: =G48*VLOOKUP($N$44,T:V,3,0) -> 0.0010005 | T48: 44 | U48: 0.0607 | V48: 0.357
T49: 45 | U49: 0.0618 | V49: 0.364
B50: Терроризм | C50: 1.2 | T50: 46 | U50: 0.063 | V50: 0.37
B51: Каменный | C51: 0.8 | T51: 47 | U51: 0.0642 | V51: 0.377
B52: Смешанный | C52: 1 | H52: 2627900.3 | I52: =H52*I47 -> 942.62785 | M52: =H52*M47 -> 2979.7762 | T52: 48 | U52: 0.0654 | V52: 0.385
B53: Деревянный | C53: 1.2 | T53: 49 | U53: 0.0667 | V53: 0.392
T54: 50 | U54: 0.068 | V54: 0.4
B55: Дом | C55: 2.2 | I55: =SUM(I37,I52) -> 942.62785 | M55: =SUM(M37,M52) -> 5936.1641 | T55: 51 | U55: 0.0694 | V55: 0.408
B56: Квартира | C56: 1 | T56: 52 | U56: 0.0708 | V56: 0.417
B57: Нежилое помещение | C57: 1,00 – 1,40 | T57: 53 | U57: 0.0723 | V57: 0.426
B58: Земельный участок | C58: 0.8 | T58: 54 | U58: 0.0739 | V58: 0.435
B59: Возраст объекта | C59: Коэффициент риска | T59: 55 | U59: 0.0756 | V59: 0.444
A60: 0 | B60: 0-20 | C60: 0.7
A61: 20 | B61: 20-29 | C61: 0.8 | T61: 56 | U61: 0.0773 | V61: 0.455
A62: 30 | B62: 30-59 | C62: 0.9 | T62: 57 | U62: 0.0791 | V62: 0.465
A63: 60 | B63: 60 | C63: 1 | T63: 58 | U63: 0.081 | V63: 0.476
A64: 61 | B64: 61 | C64: Андеррайтинг | E64: 1,1-5,00 | T64: 59 | U64: 0.0829 | V64: 0.488
T65: 60 | U65: 0.085 | V65: 0.5
T66: 61 | U66: 0.0872 | V66: 0.513
K67: РВД | L67: =Калькулятор!C19+Калькулятор!C20 -> 10 | T67: 62 | U67: 0.0895 | V67: 0.526
K68: Банк КВ | L68: =Калькулятор!C21 -> 0 | T68: 63 | U68: 0.0919 | V68: 0.541
K69: Партнерское КВ | L69: =Калькулятор!C23+Калькулятор!C24 -> 50 | T69: 64 | U69: 0.0944 | V69: 0.556
L70: =SUM(L67:L69) -> 60 | T70: 65 | U70: 0.0971 | V70: 0.571
T71: 66 | U71: 0.1 | V71: 0.588
K72: ="Партнерский Тариф с РВД " &L69 &"%" -> Партнерский Тариф с РВД 50% | T72: 67 | U72: 0.103 | V72: 0.606
G73: 0.0033 | K73: =G73*VLOOKUP($L$44,T:V,3,0) -> 0.00165 | T73: 68 | U73: 0.1063 | V73: 0.625
K74: =G74*VLOOKUP($L$44,T:V,3,0) -> 0 | T74: 69 | U74: 0.1097 | V74: 0.645
T75: 70 | U75: 0.1133 | V75: 0.667
T76: 71 | U76: 0.1172 | V76: 0.69
T77: 72 | U77: 0.1214 | V77: 0.714
T78: 73 | U78: 0.1259 | V78: 0.741
T79: 74 | U79: 0.1308 | V79: 0.769
T80: 75 | U80: 0.136 | V80: 0.8
T81: 76 | U81: 0.1417 | V81: 0.833
T82: 77 | U82: 0.1478 | V82: 0.87
T83: 78 | U83: 0.1545 | V83: 0.909
T84: 79 | U84: 0.1619 | V84: 0.952
T85: 80 | U85: 0.17 | V85: 1

Sheet Справочно
A1: БАНК | B1: КВ от АСТ | C1: Фин АСТ | D1: Предложение (ИП) | F1: Вид страхования | G1: Нетто-ставка в перестрахование | J1: Партнеры | L1: Банк | M1: КВ Банка | N1: Конструктив
A2: Сбербанк | B2: 70 | C2: 60 | D2: 50 | F2: КИС | J2: АСТ | K2: Да | L2: АбсолютБанк | M2: 50 | Q2: 0
A3: ВТБ | B3: 30 | C3: 20 | D3: 12 | F3: НС | J3: Иной | K3: Нет | L3: Акбарс | N3: Да | Q3: 0
A4: Райффайзен Банк | B4: 35 | C4: 35 | D4: 20 | F4: Им-во | G4: 0,025% | L4: Альфабанк | M4: 55 | N4: Нет | O4: 55 | Q4: 10
A5: Дом РФ | B5: 40 | C5: 20 | D5: 14 | F5: Деревянный | G5: 0,07% | L5: ВТБ | M5: 50 | N5: Да | O5: 55 | Q5: 10
A6: Связь Банк | B6: 20 | C6: 20 | F6: Каменный | G6: 0,045% | L6: ГПБ | N6: Да | Q6: 10
A7: Уралсиб | B7: 70 | C7: 20 | F7: Смешанный | G7: 0,05% | M7: 60 | N7: Да | Q7: 0
A8: АльфаБанк | B8: 70 | C8: 20 | F8: ИФЛ | L8: МКБ | N8: Да | Q8: 0
A9: АбсолютБанк | B9: 50 | C9: 20 | D9: 30 | F9: Квартира | G9: 0,046% | L9: Промсвязьбанк | N9: Нет | O9: 55 | Q9: 0
A10: КБ "Локо-Банк" (АО) | B10: 10 | C10: =B10 -> 10 | F10: Дом-дерево | G10: 0,09% | L10: Райффайзен Банк | M10: 0 | N10: Нет | O10: 55 | Q10: 10
A11: Открытие | B11: 20 | C11: =B11 -> 20 | F11: Дом-камень | G11: 0,075% | L11: РСХБ | M11: 46 | N11: Да | Q11: 10
A12: Промсвязьбанк | B12: 15 | C12: =B12 -> 15 | D12: 10 | F12: Дом-смешанный | G12: 0,070% | L12: Сбербанк | M12: 0 | N12: Да | O12: 55 | P12: 40 | Q12: 0
A13: Росбанкдом/Дельта | B13: 30 | C13: 20 | F13: Баня | G13: 0,128% | L13: Т-банк | N13: Нет | O13: 55 | Q13: 0
A14: МКБ | B14: 70 | C14: 20 | L14: Уралсиб | N14: Да | Q14: 0
A15: Юникредит | B15: 20 | C15: =B15 -> 20 | D15: 20 | L15: Юникредит | M15: 0 | N15: Нет | O15: 55 | Q15: 10
A16: Минбанк | B16: 15 | C16: =B16 -> 15 | L16: Банк СПБ | N16: Нет | O16: 55 | Q16: 0
A17: Совкомбанк | B17: 30 | C17: 20 | D17: 25
A18: Газпромбанк | B18: 20 | C18: =B18 -> 20 | D18: 20
A19: ТрансКапиталБанк/ ИНВЕСТТОРГБАНК | B19: 20 | C19: =B19 -> 20 | H19: в этом блоке требуется ввести страховую сумму, в соответствии с которой, рассчитается страховой взнос. Некоторые банки требуют 10% от остатка — ВТБ, Альфа, Райф, РСХБ, Юни Сбер, ПСБ, МКБ — 0%.
A20: Банк СПБ | B20: 35 | C20: 20 | D20: 20
A21: РСХБ | B21: 70 | C21: 20
A22: Ак Барс | B22: 25 | C22: 20
A23: Зенит | B23: 20 | C23: =B23 -> 20
A24: СМП Банк | B24: 20 | C24: =B24 -> 20
A25: Аверс | B25: 15 | C25: =B25 -> 15
A26: Автоградбанк | B26: 10 | C26: =B26 -> 10
A27: Азиатско-Тихоокеанский банк | B27: 70 | C27: 20
A28: БК Снежинский | B28: 5 | C28: =B28 -> 5
A29: АКБ Форштадт | B29: 30 | C29: 20
A30: Дальневосточный банк | B30: 15 | C30: =B30 -> 15
A31: Интеза | B31: 15 | C31: =B31 -> 15
A32: Кошелев-Банк | B32: 20 | C32: =B32 -> 20
A33: Кредит Европа Банк | B33: 20 | C33: =B33 -> 20
A34: Кузнецкбизнесбанк | B34: 5 | C34: 5
A35: Металлинвестбанк | B35: 15 | C35: 15
A36: МТС | B36: 20 | C36: 20
A37: Нико-Банк | B37: 25 | C37: 20
A38: ПримСоцБанк | B38: 50 | C38: 20
A39: СеверИнвестПроект | B39: 5 | C39: 5
A40: СКБ-БАНК | B40: 30 | C40: 20
A41: Страховое Агентство ТСБ | B41: 0 | C41: =B41 -> 0
A42: Держава | B42: 15 | C42: 15
A43: Энерготрансбанк | B43: 0 | C43: 0
A44: Москоммерцбанк | B44: 50 | C44: 20
A45: ГазНефтьбанк | B45: 20 | C45: 20
A46: РостФинанс | B46: 10 | C46: 10
A47: Банк Жилищного финансирования | B47: 15 | C47: =B47 -> 15
A48: РНКБ Банк (ПАО) | B48: 5 | C48: =B48 -> 5
A49: ПАО «Восточный экспресс банк» | B49: 15 | C49: =B49 -> 15
A50: СДМ-Банк (ПАО) | B50: 20 | C50: =B50 -> 20
A51: АО "Банк СГБ" (Севергазбанк) | B51: 20 | C51: =B51 -> 20
A52: АО КБ "Руснарбанк" | B52: 20 | C52: =B52 -> 20
A53: АО АКБ "Новикомбанк" | B53: 20 | C53: =B53 -> 20
A54: АО Банк «СНГБ» (Сургутнефтегазбанк) | B54: 15 | C54: =B54 -> 15
A55: АО АБ "РОССИЯ" | B55: 50 | C55: 20
A56: АО КБ "ФОРА-БАНК" | B56: 20 | C56: =B56 -> 20
A57: АБ КБ "Солидарность" (Предыдущее название МИА) | B57: 10 | C57: =B57 -> 10
A58: УБРиР | B58: 15 | C58: =B58 -> 15
A59: ООО "Агентская компания "ГАМБИТ" | B59: 20 | C59: =B59 -> 20
A60: ПАО Новосибирский социальный коммерческий банк "Левобережный" | B60: 15 | C60: =B60 -> 15
A61: ООО "Ригванс" | B61: 0 | C61: =B61 -> 0
A62: ООО "БИЗНЕС СИТИ" | B62: 5 | C62: =B62 -> 5
A63: АО "БМ-Банк" | B63: 10 | C63: =B63 -> 10
A64: ООО "ПАЙК ПЛЕЙС" | B64: 15 | C64: =B64 -> 15
A65: ООО "Горизонт страховой брокер" | B65: 10 | C65: =B65 -> 10
A66: ПАО Банк Синара | B66: 30 | C66: 20
A67: ООО "СОВКОМКАР Д" | B67: 10 | C67: =B67 -> 10
A68: ООО "Инвестлизинг" | B68: 0 | C68: =B68 -> 0
A69: ООО "Хоум Кредит энд Финанс Банк" | B69: 5 | C69: =B69 -> 5
A70: АКБ "Энергобанк" | B70: 25 | C70: 20
A71: АО "Всероссийский Банк Развития Регионов" | B71: 45 | C71: 20
A72: АКЦЕПТ БАНК (Новосибирск) | B72: 10 | C72: =B72 -> 10
A73: АЛМАЗЭРГИЭНБАНК (АЭБ) | B73: 20 | C73: =B73 -> 20
A74: СОБИНБАНК | B74: 30 | C74: 20
A75: СОЮЗ БАНК | B75: 30 | C75: 20
A76: Запсибкомбанк (ПАО) | B76: 30 | C76: 20
A77: СИБИРСКИЙ СОЦИАЛЬНЫЙ БАНК (ООО Сибсоцбанк) | B77: 50 | C77: 20
A78: Финсервис (АО) | B78: 20 | C78: =B78 -> 20
A79: Центр-инвест (ПАО КБ) | B79: 50 | C79: 20
A80: Национальная Фабрика Ипотеки (НФИ) только переход | B80: 10 | C80: =B80 -> 10
A81: Кубань Кредит | B81: 10 | C81: =B81 -> 10
A82: Татсоцбанк | B82: 10 | C82: =B82 -> 10
A83: Оренбург | B83: 40 | C83: 20
A84: НС банк | B84: 10 | C84: =B84 -> 10
A85: Первый Клиентский Банк | B85: 20 | C85: =B85 -> 20
A86: СимплФинанс | B86: 10 | C86: =B86 -> 10
A87: ПКБ-ЭкспертФин | B87: 10 | C87: =B87 -> 10
A88: Столичная сберегательная компания | B88: 10 | C88: =B88 -> 10
A89: Банк ИПБ (Интерпрогресс) | B89: 30 | C89: 20
A90: Яндекс | B90: 45 | C90: 20
A91: Свой Банк | B91: 10 | C91: =B91 -> 10
A92: ДрайвКликБанк | B92: 50 | C92: 20
A93: АО "ОТП банк" | B93: 20 | C93: =B93 -> 20
A94: АО "Мираф-банк" | B94: 35 | C94: 20
A95: ББР Банк (АО) | B95: 25 | C95: 20
A96: АО Толяттихимбанк | B96: 20 | C96: =B96 -> 20
A97: Гринфинанс | B97: 20 | C97: =B97 -> 20
A98: ООО "ФинансПрф-Агент" | B98: 15 | C98: =B98 -> 15
A99: ООО Банк Оранжевый | B99: 20 | C99: =B99 -> 20
A100: ПАО "Уральский банк реконструкции и развития" | B100: 5 | C100: =B100 -> 5
...

Sheet Новый проект
E1: СС
E2: 1000000 | G2: Максимальные тарифы
A3: М | B3: Ж | E3: М | F3: Ж | G3: М | H3: Ж
A4: 590 | B4: 2980 | C4: =B4/A4 -> 5.0508475 | D4: 30 | E4: =$E$2/A4 -> 1694.9153 | F4: =$E$2/B4 -> 335.57047 | G4: =E4/$E$2 -> 0.0016949153 | H4: =F4/$E$2 -> 0.00033557047
A5: 450 | B5: 1430 | C5: =B5/A5 -> 3.1777778 | D5: 40 | E5: =$E$2/A5 -> 2222.2222 | F5: =$E$2/B5 -> 699.3007 | G5: =E5/$E$2 -> 0.0022222222 | H5: =F5/$E$2 -> 0.0006993007
A6: 200 | B6: 630 | C6: =B6/A6 -> 3.15 | D6: 50 | E6: =$E$2/A6 -> 5000 | F6: =$E$2/B6 -> 1587.3016 | G6: =E6/$E$2 -> 0.005 | H6: =F6/$E$2 -> 0.0015873016
A7: 80 | B7: 230 | C7: =B7/A7 -> 2.875 | D7: 60 | E7: =$E$2/A7 -> 12500 | F7: =$E$2/B7 -> 4347.8261 | G7: =E7/$E$2 -> 0.0125 | H7: =F7/$E$2 -> 0.0043478261
A8: 30 | B8: 90 | C8: =B8/A8 -> 3 | D8: 70 | E8: =$E$2/A8 -> 33333.333 | F8: =$E$2/B8 -> 11111.111 | G8: =E8/$E$2 -> 0.033333333 | H8: =F8/$E$2 -> 0.011111111
A9: 10 | B9: 20 | C9: =B9/A9 -> 2 | E9: =$E$2/A9 -> 100000 | F9: =$E$2/B9 -> 50000 | G9: =E9/$E$2 -> 0.1 | H9: =F9/$E$2 -> 0.05
E12: СС
E13: 1000000 | G13: Максимальные тарифы
A14: М | B14: Ж | E14: М | F14: Ж | G14: М | H14: Ж
A15: 233 | B15: 466 | C15: =B15/A15 -> 2 | D15: 30 | E15: =$E$2/A15 -> 4291.8455 | F15: =$E$2/B15 -> 2145.9227 | G15: =E15/$E$2 -> 0.0042918455 | H15: =F15/$E$2 -> 0.0021459227 | J15: =0.3%*E13 -> 3000 | K15: =J15*A15 -> 699000
A16: 117 | B16: 251 | C16: =B16/A16 -> 2.1452991 | D16: 40 | E16: =$E$2/A16 -> 8547.0085 | F16: =$E$2/B16 -> 3984.0637 | G16: =E16/$E$2 -> 0.0085470085 | H16: =F16/$E$2 -> 0.0039840637 | J16: =E13*0.5% -> 5000 | K16: =J16*A15 -> 1165000
A17: 59 | B17: 130 | C17: =B17/A17 -> 2.2033898 | D17: 50 | E17: =$E$2/A17 -> 16949.153 | F17: =$E$2/B17 -> 7692.3077 | G17: =E17/$E$2 -> 0.016949153 | H17: =F17/$E$2 -> 0.0076923077 | J17: =J15/(1-0.9) -> 30000 | K17: =J17*A15 -> 6990000
A18: 28 | B18: 63 | C18: =B18/A18 -> 2.25 | D18: 60 | E18: =$E$2/A18 -> 35714.286 | F18: =$E$2/B18 -> 15873.016 | G18: =E18/$E$2 -> 0.035714286 | H18: =F18/$E$2 -> 0.015873016 | J18: =J17*0.9 -> 27000
A19: 7 | B19: 11 | C19: =B19/A19 -> 1.5714286 | D19: 70 | E19: =$E$2/A19 -> 142857.14 | F19: =$E$2/B19 -> 90909.091 | G19: =E19/$E$2 -> 0.14285714 | H19: =F19/$E$2 -> 0.090909091
A20: 3 | B20: 4 | C20: =B20/A20 -> 1.3333333 | E20: =$E$2/A20 -> 333333.33 | F20: =$E$2/B20 -> 250000 | G20: =E20/$E$2 -> 0.33333333 | H20: =F20/$E$2 -> 0.25

Sheet Матрица КВ
I1: Прямой | J1: Ограничение на общую нагрузку
I2: Скидка | J2: 20% от лучшей цены для сотрудников
A3: БАНК | B3: АСТ | C3: Прямой | D3: Через банк | E3: Сравниру* | F3: Финуслуги | G3: Банкиру | I3: Через банк | J3: КВ по нашей информации
A4: Сбербанк | B4: 60 | C4: 55 | D4: 0 | E4: 70 | F4: 70 | I4: Сравни ру | J4: через их агентский канал
A5: ВТБ | B5: 25 | C5: 55 | D5: 50 | E5: 70 | F5: 65 | I5: Банки ру — информация об осаго и каско (500 000р в месяц)
A6: Дом РФ | B6: 20 | C6: 55 | D6: 60 | E6: 70 | F6: 60 | J6: Банк | K6: ВТБ
A7: АльфаБанк | B7: 20 | C7: 55 | D7: 55 | E7: 70 | J7: РВД | K7: 5
A8: РСХБ | B8: 25 | C8: 55 | D8: 46 | E8: 70 | J8: Банк КВ | K8: =IFERROR(VLOOKUP(K6,Справочно!L2:M20,2,0),"Добавь банк") -> 50
A9: Райффайзен Банк | B9: 35 | C9: 55 | F9: 55 | J9: Партнер | K9: Иной
A10: Азиатско-Тихоокеанский банк | B10: 30 | C10: 55 | J10: Партнерское КВ | K10: =IF(K9="АСТ",VLOOKUP(K6,#REF!,3,0),0) -> 0
A11: МКБ | B11: 30 | C11: 55 | J11: Общая нагрузка | K11: =SUM(K7:K10) -> 55
A12: Газпромбанк | B12: 20 | C12: 55 | D12: 50
A13: Совкомбанк | B13: 30 | C13: 55
A14: Юникредит | B14: 20 | C14: 55 | F14: 60
A15: Промсвязьбанк | B15: 15 | C15: 55
A16: Связь Банк | B16: 20 | C16: 55
A17: Уралсиб | B17: 30 | C17: 55
A18: АбсолютБанк | B18: 20 | C18: 55 | D18: 50
A19: КБ "Локо-Банк" (АО) | B19: 10 | C19: 55
A20: Открытие | B20: 20 | C20: 55
A21: Росбанкдом/Дельта | B21: 30 | C21: 55
A22: Минбанк | B22: 15 | C22: 55
A23: ТрансКапиталБанк/ ИНВЕСТТОРГБАНК | B23: 20 | C23: 55
A24: ПАО "Банк "Санкт-Петербург" | B24: 25 | C24: 55
A25: Ак Барс | B25: 25 | C25: 55
A26: Зенит | B26: 20 | C26: 55
A27: СМП Банк | B27: 20 | C27: 55
A28: Аверс | B28: 15 | C28: 55
A29: Автоградбанк | B29: 10 | C29: 55
A30: БК Снежинский | B30: 5 | C30: 55
... A104: Стройлесбанк | B104: 25 | C104: 55

Sheet Ставки со сравни
A2: сбер | E2: РГС | J2: евроинс | L2: Согаз
A3: им | B3: 38 | C3: 45 | D3: 41 | E3: 65 | F3: 45 | G3: 45 | H3: 55 | I3: 50 | J3: 60 | K3: 50 | L3: 50 | M3: =AVERAGE(B3:L3) -> 49.454545
A4: ж | B4: 41 | E4: 65 | F4: 45 | G4: 45 | H4: 55 | I4: 50 | J4: 50 | L4: 50 | M4: =AVERAGE(B4:L4) -> 50.125
A6: ВТБ
A7: им | B7: 15 | C7: 15 | D7: 8 | E7: 8 | F7: 15 | G7: 15 | H7: 12 | I7: 8 | J7: 8 | K7: 8 | M7: =AVERAGE(B7:L7) -> 11.2
A8: ж | B8: 15 | C8: 15 | D8: 8 | E8: 8 | F8: 15 | G8: 15 | H8: 12 | I8: 8 | J8: 8 | K8: 8 | M8: =AVERAGE(B8:L8) -> 11.2
E10: Акбарс | H10: РСХБ
A11: райф | B11: 8 | C11: 19 | D11: 8 | E11: 45 | F11: 8 | G11: 8 | H11: 55 | I11: 15 | J11: 12 | M11: =AVERAGE(B11:J11) -> 19.777778
B12: 8 | C12: 19 | D12: 8 | E12: 45 | F12: 8 | G12: 8 | H12: 55 | I12: 15 | J12: 12 | M12: =AVERAGE(B12:L12) -> 19.777778
A14: ДомРФ | B14: согласие | C14: росбанк | D14: ренин | E14: Акбарс | F14: альфа | G14: пари | H14: энерго
B15: 11 | C15: 8 | D15: 12 | E15: 45 | F15: 4 | G15: 8 | H15: 10 | M15: =AVERAGE(B15:L15) -> 14
B16: 11 | C16: 8 | D16: 12 | F16: 4 | G16: 8 | H16: 10 | M16: =AVERAGE(B16:H16) -> 8.8333333
A18: Абсол | B18: Евро | C18: Юго | D18: Согл | E18: Пари | F18: Абсолю | G18: Акбарс
B19: 15 | C19: 45 | D19: 15 | E19: 25 | F19: 15 | G19: 45 | M19: =AVERAGE(B19:L19) -> 26.666667
A22: ПСБ | B22: евро | C22: энерг | D22: юг | E22: Пари | F22: совком | G22: Акбарс | H22: зетта
B23: 10 | C23: 10 | D23: 4 | E23: 8 | F23: 6 | G23: 45 | H23: 10 | M23: =AVERAGE(B23:L23) -> 13.285714
B24: 10 | C24: 10 | D24: 4 | E24: 8 | F24: 6 | H24: 10 | M24: =AVERAGE(B24:H24) -> 8
A26: Юни | B26: энер | C26: Рсхб | D26: акбарс | E26: абс | F26: пари | G26: альфа
B27: 15 | C27: 55 | D27: 45 | E27: 26 | F27: 8 | G27: 4 | M27: =AVERAGE(B27:L27) -> 25.5
A29: Совком | B29: акб | C29: зетт | D29: юго | E29: пари
B30: 45 | C30: 18 | D30: 23 | E30: 8 | M30: =AVERAGE(B30:L30) -> 23.5
A32: ГПБ | B32: акб | C32: пари | D32: зет | E32: согл | F32: альфа | G32: юг
B33: 45 | C33: 8 | D33: 9.76 | E33: 33 | F33: 8 | G33: 8 | M33: =AVERAGE(B33:L33) -> 18.626667
A35: Санкт-Петербург | B35: Акб | C35: энерг | D35: юго | E35: пари | F35: зетта | G35: согл
B36: 45 | C36: 0 | D36: 15 | E36: 8 | F36: 18 | G36: 23 | M36: =AVERAGE(B36:L36) -> 18.166667
A38: Тбанк | B38: энер | C38: пари | D38: акбарс
B39: 4 | C39: 8 | D39: 45 | M39: =AVERAGE(B39:L39) -> 19

Sheet РНПК
A1: возраст | B1: мужчины | C1: женщины | E1: мужчины | F1: женщины
A2: 18 | B2: 0.0434 | C2: 0.0238 | D2: 18-20 | E2: =AVERAGE(B2:B4) -> 0.050866667 | F2: =AVERAGE(C2:C4) -> 0.0252 | G2: 18 | H2: 20
A3: 19 | B3: 0.0504 | C3: 0.0252 | D3: 21-25 | E3: =AVERAGE(B5:B9) -> 0.07168 | F3: =AVERAGE(C5:C9) -> 0.02912 | G3: 21 | H3: 25
A4: 20 | B4: 0.0588 | C4: 0.0266 | D4: =G4&"-"&H4 -> 26-27 | E4: =AVERAGE(B10:B11) -> 0.0777 | F4: =AVERAGE(C10:C11) -> 0.0322 | G4: =H3+1 -> 26 | H4: 27
A5: 21 | B5: 0.0658 | C5: 0.028 | D5: =G5&"-"&H5 -> 28-29 | E5: =AVERAGE(B12:B13) -> 0.0854 | F5: =AVERAGE(C12:C13) -> 0.0364 | G5: =H4+1 -> 28 | H5: 29
A6: 22 | B6: 0.07 | C6: 0.028 | D6: =G6&"-"&H6 -> 30-31 | E6: =AVERAGE(B14:B15) -> 0.098 | F6: =AVERAGE(C14:C15) -> 0.0399 | G6: =H5+1 -> 30 | H6: 31
A7: 23 | B7: 0.0728 | C7: 0.0294 | D7: =G7&"-"&H7 -> 32-33 | E7: =AVERAGE(B16:B17) -> 0.1064 | F7: =AVERAGE(C16:C17) -> 0.042 | G7: =H6+1 -> 32 | H7: 33
A8: 24 | B8: 0.0742 | C8: 0.0294 | D8: =G8&"-"&H8 -> 34-35 | E8: =AVERAGE(B18:B19) -> 0.1211 | F8: =AVERAGE(C18:C19) -> 0.049 | G8: =H7+1 -> 34 | H8: 35
A9: 25 | B9: 0.0756 | C9: 0.0308 | D9: =G9&"-"&H9 -> 36-37 | E9: =AVERAGE(B20:B21) -> 0.1358 | F9: =AVERAGE(C20:C21) -> 0.0553 | G9: =H8+1 -> 36 | H9: 37
A10: 26 | B10: 0.077 | C10: 0.0308 | D10: =G10&"-"&H10 -> 38-39 | E10: =AVERAGE(B22:B23) -> 0.1547 | F10: =AVERAGE(C22:C23) -> 0.0637 | G10: =H9+1 -> 38 | H10: 39
A11: 27 | B11: 0.0784 | C11: 0.0336 | D11: =G11&"-"&H11 -> 40-41 | E11: =AVERAGE(B24:B25) -> 0.1778 | F11: =AVERAGE(C24:C25) -> 0.0728 | G11: =H10+1 -> 40 | H11: 41
A12: 28 | B12: 0.0826 | C12: 0.035 | D12: =G12&"-"&H12 -> 42-43 | E12: =AVERAGE(B26:B27) -> 0.2009 | F12: =AVERAGE(C26:C27) -> 0.0854 | G12: =H11+1 -> 42 | H12: 43
A13: 29 | B13: 0.0882 | C13: 0.0378 | D13: =G13&"-"&H13 -> 44-46 | E13: =AVERAGE(B28:B30) -> 0.23846667 | F13: =AVERAGE(C28:C30) -> 0.10826667 | G13: =H12+1 -> 44 | H13: 46
A14: 30 | B14: 0.0952 | C14: 0.0392 | D14: =G14&"-"&H14 -> 47-49 | E14: =AVERAGE(B31:B33) -> 0.29633333 | F14: =AVERAGE(C31:C33) -> 0.14326667 | G14: =H13+1 -> 47 | H14: 49
A15: 31 | B15: 0.1008 | C15: 0.0406 | D15: =G15&"-"&H15 -> 50-52 | E15: =AVERAGE(B34:B36) -> 0.3612 | F15: =AVERAGE(C34:C36) -> 0.1708 | G15: =H14+1 -> 50 | H15: 52
A16: 32 | B16: 0.1036 | C16: 0.0406 | D16: =G16&"-"&H16 -> 53-55 | E16: =AVERAGE(B37:B39) -> 0.45313333 | F16: =AVERAGE(C37:C39) -> 0.21233333 | G16: =H15+1 -> 53 | H16: 55
A17: 33 | B17: 0.1092 | C17: 0.0434 | D17: =G17&"-"&H17 -> 56-58 | E17: =AVERAGE(B40:B42) -> 0.54973333 | F17: =AVERAGE(C40:C42) -> 0.2772 | G17: 56 | H17: 58
A18: 34 | B18: 0.1176 | C18: 0.0476 | D18: =G18&"-"&H18 -> 59-63 | E18: =AVERAGE(B43:B47) -> 0.70392 | F18: =AVERAGE(C43:C47) -> 0.41748 | G18: 59 | H18: 63
A19: 35 | B19: 0.1246 | C19: 0.0504 | D19: =G19&"-"&H19 -> 64-65 | E19: =AVERAGE(B48:B49) -> 0.8666 | F19: =AVERAGE(C48:C49) -> 0.5894 | G19: 64 | H19: 65
A20: 36 | B20: 0.1316 | C20: 0.0532
A21: 37 | B21: 0.14 | C21: 0.0574
A22: 38 | B22: 0.1484 | C22: 0.0616
A23: 39 | B23: 0.161 | C23: 0.0658
A24: 40 | B24: 0.1722 | C24: 0.07
A25: 41 | B25: 0.1834 | C25: 0.0756
A26: 42 | B26: 0.1946 | C26: 0.0812
A27: 43 | B27: 0.2072 | C27: 0.0896
A28: 44 | B28: 0.2226 | C28: 0.098
A29: 45 | B29: 0.238 | C29: 0.1078
A30: 46 | B30: 0.2548 | C30: 0.119
A31: 47 | B31: 0.2758 | C31: 0.1316
... A49: 65 | B49: 0.8932 | C49: 0.6188

Sheet триггеры
C2: Возраст застрахованного лица, полных лет | D2: СС
C3: от 18 до 34 лет включительно | D3: начиная с 55 000 000
A4: 1. Страховая сумма: свыше 7 млн при хорошем риске | C4: от 35 до 44 лет включительно | D4: начиная с 40 000 000
A5: 2. Нагрузка: Общая нагрузка выше 55%, при этом она состоит из: | C5: от 45 до 54 лет включительно | D5: начиная с 35 000 000
A6: Партнерское КВ | C6: от 55 до 64 лет включительно | D6: начиная с 15 000 000
A7: РВД - 5% всегда | C7: от 65 лет и старше | D7: при любой сумме
A8: Прочее (прибыль)
A9: По сберу выше 65% (5% РВД + КВ - 60%)
A10: 3. Нестандарт (например, хроника/операции)
A11: 4. Запрос терроризма более 3 млн.
A12: 5. Деревянный дом
A13: 6. Территория вне аппетита (Москва, СПб, Московская область, Ленинградская область)
A14: 7. Возраст страхователей (от 18 до 60)
A15: 8. Все запросы должны направляться в СБ на проверку страхователей по открытым источникам. СБ должна фиксировать проверку в трекере. При оценке на желтом или красном уровнях - направление на согласование в РГ.
A17: Если возраст молодой, то 40% попробовать тарифы.
A19: LoCker_12
A21: СА
A22: Старше 65 лет по НС, если первичный договор
... A29: Специальный акцепт по договорам сострахования в зависимости от размера страховой суммы (по договорам коллективного страхования) Перестрахование риска выплаты страхового возмещения по договорам сострахования осуществляется на основании специального акцепта перестраховщика, только если общая страховая сумма по договору сострахования с учетом всех застрахованных рисков по одному застрахованному лицу равна либо превышает 250 млн. рублей.

Sheet Сроки
D4: 50
A5: 45988 | B5: 46352 | D5: =D4+E5 -> 51 | E5: 1
A6: 46353 | B6: 46717 | C6: 1 | D6: =D5+E6 -> 52 | E6: 1
A7: 46718 | B7: 47083 | C7: 2 | D7: =D6+E7 -> 53 | E7: 1
A8: 47084 | B8: 47448 | C8: 3 | D8: =D7+E8 -> 54 | E8: 1
A9: 47449 | B9: 47813 | C9: 4 | D9: =D8+E9 -> 55 | E9: 1
A10: 47814 | B10: 48178 | C10: 5 | D10: =D9+E10 -> 56 | E10: 1
A11: 48179 | B11: 48544 | C11: 6 | D11: =D10+E11 -> 57 | E11: 1
A12: 48545 | B12: 48909 | C12: 7 | D12: =D11+E12 -> 58 | E12: 1
A13: 48910 | B13: 49274 | C13: 8 | D13: =D12+E13 -> 59 | E13: 1
A14: 49275 | B14: 49639 | C14: 9 | D14: =D13+E14 -> 60 | E14: 1
A15: 49640 | B15: 50005 | C15: 10 | D15: =D14+E15 -> 61 | E15: 1
A16: 50006 | B16: 50370 | C16: 11 | D16: =D15+E16 -> 62 | E16: 1
A17: 50371 | B17: 50735 | C17: 12 | D17: =D16+E17 -> 63 | E17: 1
... A21: 51832 | B21: 15368 | C21: 16 | D21: =D20+E21 -> 67 | E21: 1
